{
  "id": 16,
  "title_ja": "ひらがな：さ (Sa)",
  "title_th": "อักษรฮิรางาเนะ: さ (Sa)",
  "category": "Hiragana (ひらがな)",
  "category_th": "ระดับ 1: อักษรฮิรางาเนะ",
  "char": "さ",
  "stroke_count": 3,
  "how_to_write_ja": "1. 横一文字を少し右上がりに。2. 斜めに下ろして右上で跳ねる。3. 下に受け皿の短い弧を置く。",
  "how_to_write_th": "1. ขีดเฉียงขวาบนเล็กน้อย 2. ลากดิ่งลงตัดลาดตวัดขึ้น 3. ขีดประคองด้านล่างหงายรับอารมณ์ปลายพู่",
  "important_phrases": [
    {
      "phrase_ja": "さかな",
      "romaji": "sakana",
      "meaning_ja": "魚",
      "meaning_th": "ปลา",
      "hint": "วัตถุดิบขึ้นชื่อโภชนาการโตเกียว"
    },
    {
      "phrase_ja": "さくら",
      "romaji": "sakura",
      "meaning_ja": "桜",
      "meaning_th": "ดอกซากุระ",
      "hint": "สัญลักษณ์ตัวแทนแห่งฤดูใบไม้ผลิ"
    }
  ],
  "explanation_th": "ตัวอักษร <strong>さ (sa)</strong> ชวนสับสนกับ <strong>き (ki)</strong> ได้ง่ายเนื่องจากเขียนเกือบเหมือนกัน แต่ さ มีเพียงขีดขวางแรกเพียวๆ ขีดเดียวประหยัดแรงมือ",
  "tip_th": "เตือนความจำ: き มี 2 ขีดขนาน แต่ さ มีเพียง 1 ขีดข้ามตรงหน้า จำได้ขึ้นใจไม่มีสับสนคลาดเคลื่อน!",
  "meta_description": "จำและแยกแยะอักษร さ (Sa) วิธีการวาดเขียนสัดส่วนพร้อมปลา (sakana) และซากุระ (sakura) สดสวย"
}