{
  "id": 192,
  "title_ja": "「～たいです」で願望を表現する",
  "title_th": "อยากได้... 「～たいです」を使って表現する (ความหมายของภาษาไทย)",
  "category": "Grammar (文法)",
  "category_th": "ระดับ 5: ไวยากรณ์น่ารู้ (Vocabulary & Grammar)",
  "char": "~たいです",
  "stroke_count": 8,
  "how_to_write_ja": "～たいですを使った願望は、自分の希望や願いを表現するために使用されます。  例えば、「食べたい」という願望を表すときは、「私は食べたい。」となります。",
  "how_to_write_th": "อยากได้... 「～たいです」ใช้แสดงความต้องการหรือสิ่งที่ต้องการจะได้รับ  เช่น “อยากกิน” จะใช้เป็นภาษาไทย เช่น “ฉันอยากกินข้าว.”",
  "important_phrases": [
    {
      "phrase_ja": "私は～たいです",
      "romaji": "Watashi wa ~tai desu",
      "meaning_ja": "I want/desire... (meaning in Kanji/Hiragana)",
      "meaning_th": "ฉันอยากได้...",
      "hint": "ใช้กับสิ่งที่ต้องการในชีวิตประจำวัน เช่น ฉันอยากกินข้าว หรือฉันอยากเรียนภาษาอังกฤษ"
    },
    {
      "phrase_ja": "～たいです",
      "romaji": "Ta desu.",
      "meaning_ja": "This is how to say in Japanese",
      "meaning_th": "ต้องการนี้",
      "hint": "ใช้แสดงความอยากได้และความตั้งใจในการพูดภาษาไทย"
    }
  ],
  "explanation_th": "～たいです は、Japanese の文法で使う表現ですね。これは「〜たい」という願望を表す言葉になります。例えば、「食べたい」という願望を表すときは、「私は食べたい。」となります。",
  "tip_th": "~たいです の使い方を学ぶ際は、実際に日本語で練習してみましょう。\n   - 具体的な願望を述べると、より自然な表現になるでしょう。 \n   - また、相手が理解しやすいように、丁寧な表現を使うことも重要です。",
  "meta_description": "ภาษาไทยที่เป็นธรรมชาติและสุภาพ - แสดงความอยากได้ในภาษาไทย \"～たい desu\" | Japanese grammar lesson for Thai speakers | ความหมายและวิธีการใช้งาน"
}